pkcs7/__init__.py
pkcs7/pkcs7.py
pkcs7_detached/__init__.py
pkcs7_detached/aws_certificates.py
pkcs7_detached-0.0.3.dist-info/LICENSE
pkcs7_detached-0.0.3.dist-info/METADATA
pkcs7_detached-0.0.3.dist-info/WHEEL
pkcs7_detached-0.0.3.dist-info/top_level.txt
pkcs7_detached-0.0.3.dist-info/RECORD
