Metadata-Version: 2.1
Name: pkcs7-detached
Version: 0.0.3
Summary: Validate PKCS7 detached signatures
Home-page: https://github.com/jnewbigin/pkcs7_detached
Author: John Newbigin
Author-email: jnewbigin@chrysocome.net
License: UNKNOWN
Platform: UNKNOWN
Classifier: Programming Language :: Python :: 3
Classifier: License :: OSI Approved :: MIT License
Classifier: Operating System :: OS Independent
Requires-Dist: cryptography (>=2.3)
